retinasdk/__init__.py
retinasdk/full_client.py
retinasdk/lite_client.py
retinasdk/client/__init__.py
retinasdk/client/base_client.py
retinasdk/client/classify_api.py
retinasdk/client/compare_api.py
retinasdk/client/exceptions.py
retinasdk/client/expressions_api.py
retinasdk/client/image_api.py
retinasdk/client/retinas_api.py
retinasdk/client/terms_api.py
retinasdk/client/text_api.py
retinasdk/model/__init__.py
retinasdk/model/category_filter.py
retinasdk/model/context.py
retinasdk/model/fingerprint.py
retinasdk/model/image.py
retinasdk/model/language_rest.py
retinasdk/model/metric.py
retinasdk/model/retina.py
retinasdk/model/term.py
retinasdk/model/text.py
retinasdk-1.0.0.dist-info/DESCRIPTION.rst
retinasdk-1.0.0.dist-info/METADATA
retinasdk-1.0.0.dist-info/RECORD
retinasdk-1.0.0.dist-info/WHEEL
retinasdk-1.0.0.dist-info/metadata.json
retinasdk-1.0.0.dist-info/top_level.txt
