Metadata-Version: 2.0
Name: retinasdk
Version: 1.0.0
Summary: Client library for accessing Cortical.io's Retina API.
Home-page: https://github.com/cortical-io/retina-sdk.py
Author: cortical.io Team
Author-email: teamvienna@cortical.io
License: BSD
Keywords: semantic text processing language
Platform: UNKNOWN
Classifier: Development Status :: 5 - Production/Stable
Classifier: Intended Audience :: Developers
Classifier: Intended Audience :: Science/Research
Classifier: Topic :: Text Processing :: Linguistic
Classifier: License :: OSI Approved :: BSD License
Classifier: Programming Language :: Python
Classifier: Programming Language :: Python :: 2
Classifier: Programming Language :: Python :: 2.6
Classifier: Programming Language :: Python :: 2.7
Classifier: Programming Language :: Python :: 3
Classifier: Programming Language :: Python :: 3.4
Classifier: Operating System :: MacOS :: MacOS X
Classifier: Operating System :: POSIX :: Linux
Classifier: Operating System :: Microsoft :: Windows
Requires-Dist: requests
